figgis/__init__.py
figgis/_version.py
figgis-1.8.1.dist-info/DESCRIPTION.rst
figgis-1.8.1.dist-info/METADATA
figgis-1.8.1.dist-info/RECORD
figgis-1.8.1.dist-info/WHEEL
figgis-1.8.1.dist-info/metadata.json
figgis-1.8.1.dist-info/top_level.txt
