Metadata-Version: 2.0
Name: figgis
Version: 1.8.1
Summary: Python declarative data validation
Home-page: https://github.com/thesquelched/figgis
Author: Scott Kruger
Author-email: scott@chojin.org
License: UNKNOWN
Download-URL: https://github.com/thesquelched/figgis/tarball/1.8.1
Platform: UNKNOWN
Classifier: Development Status :: 5 - Production/Stable
Classifier: Intended Audience :: Developers
Classifier: License :: OSI Approved :: Apache Software License
Classifier: Operating System :: OS Independent
Classifier: Programming Language :: Python :: 2.6
Classifier: Programming Language :: Python :: 2.7
Classifier: Programming Language :: Python :: 3
Classifier: Topic :: Software Development :: Libraries
Requires-Dist: six
